{
  "_id": "bkipkPpDNi2Oo3re",
  "name": "Escape & Evasion Kit",
  "type": "item",
  "data": {
    "description": "<p>These kits contained a small compass, tiny hacksaw, silk map, and local currency (~$20). Issued mainly to airborne and covert operatives.</p>",
    "quantity": {
      "value": 1,
      "max": 0
    },
    "tags": [],
    "treasure": false,
    "weight": 0
  },
  "sort": 500000,
  "flags": {
    "exportSource": {
      "world": "owb",
      "system": "owb",
      "coreVersion": "0.7.9",
      "systemVersion": "0.1.7"
    }
  },
  "img": "modules/owb-content/assets/default/map.png",
  "effects": []
}