{
  "_id": "GGMcuMztb5nodhiZ",
  "name": "Field Rations (1-day)",
  "type": "item",
  "data": {
    "description": "<p>These canned, bland-tasting, precooked rations were issued to most military troops in one form or another. They were initially intended to be used sparingly, but food shortages and issues with supply lines sometimes forced soldiers to eat field rations for weeks at a time.</p>",
    "quantity": {
      "value": 1,
      "max": 0
    },
    "tags": [],
    "treasure": false,
    "weight": 1
  },
  "sort": 700000,
  "flags": {
    "exportSource": {
      "world": "owb",
      "system": "owb",
      "coreVersion": "0.7.9",
      "systemVersion": "0.1.7"
    }
  },
  "img": "modules/owb-content/assets/default/food.png",
  "effects": []
}